TinyPythonEs6Notebook/README.md
TinyPythonEs6Notebook/__init__.py
TinyPythonEs6Notebook/__main__.py
TinyPythonEs6Notebook/file.epub
TinyPythonEs6Notebook/index.html
TinyPythonEs6Notebook/css/__init__.py
TinyPythonEs6Notebook/css/annotations.css
TinyPythonEs6Notebook/css/main.css
TinyPythonEs6Notebook/css/normalize.css
TinyPythonEs6Notebook/css/popup.css
TinyPythonEs6Notebook/font/__init__.py
TinyPythonEs6Notebook/font/fontello.eot
TinyPythonEs6Notebook/font/fontello.svg
TinyPythonEs6Notebook/font/fontello.ttf
TinyPythonEs6Notebook/font/fontello.woff
TinyPythonEs6Notebook/img/__init__.py
TinyPythonEs6Notebook/img/annotator-glyph-sprite.png
TinyPythonEs6Notebook/img/annotator-icon-sprite.png
TinyPythonEs6Notebook/img/apple-touch-icon.png
TinyPythonEs6Notebook/img/cancelfullscreen.png
TinyPythonEs6Notebook/img/close.png
TinyPythonEs6Notebook/img/fullscreen.png
TinyPythonEs6Notebook/img/loader.gif
TinyPythonEs6Notebook/img/menu-icon.png
TinyPythonEs6Notebook/img/save.png
TinyPythonEs6Notebook/img/saved.png
TinyPythonEs6Notebook/img/settings-s.png
TinyPythonEs6Notebook/img/settings.png
TinyPythonEs6Notebook/img/star.png
TinyPythonEs6Notebook/js/__init__.py
TinyPythonEs6Notebook/js/epub.js
TinyPythonEs6Notebook/js/epub.min.js
TinyPythonEs6Notebook/js/epub.min.map
TinyPythonEs6Notebook/js/hooks.min.js
TinyPythonEs6Notebook/js/hooks.min.map
TinyPythonEs6Notebook/js/reader.js
TinyPythonEs6Notebook/js/reader.js.map
TinyPythonEs6Notebook/js/reader.min.js
TinyPythonEs6Notebook/js/reader.min.map
TinyPythonEs6Notebook/js/hooks/__init__.py
TinyPythonEs6Notebook/js/hooks/extensions/__init__.py
TinyPythonEs6Notebook/js/hooks/extensions/highlight.js
TinyPythonEs6Notebook/js/libs/__init__.py
TinyPythonEs6Notebook/js/libs/jquery.min.js
TinyPythonEs6Notebook/js/libs/localforage.min.js
TinyPythonEs6Notebook/js/libs/screenfull.js
TinyPythonEs6Notebook/js/libs/screenfull.min.js
TinyPythonEs6Notebook/js/libs/zip.min.js
TinyPythonEs6Notebook/js/plugins/__init__.py
tiny_python_es6_notebook-2024.3.2.0.dist-info/METADATA
tiny_python_es6_notebook-2024.3.2.0.dist-info/WHEEL
tiny_python_es6_notebook-2024.3.2.0.dist-info/entry_points.txt
tiny_python_es6_notebook-2024.3.2.0.dist-info/top_level.txt
tiny_python_es6_notebook-2024.3.2.0.dist-info/RECORD
